sd_utils/__init__.py
sd_utils/sd_cache.py
sd_utils/sd_checks.py
sd_utils/sd_config.py
sd_utils/sd_ddf.py
sd_utils/sd_load.py
sd_utils/sd_log.py
sd_utils/sd_xds.py
SDUtils-2.6.4.dist-info/METADATA
SDUtils-2.6.4.dist-info/WHEEL
SDUtils-2.6.4.dist-info/top_level.txt
SDUtils-2.6.4.dist-info/RECORD
