Metadata-Version: 2.1
Name: SDUtils
Version: 2.6.4
Summary: StratoDem utilities
Home-page: https://github.com/StratoDem/SDUtils
Author: StratoDem Analytics
Author-email: tech@stratodem.com
License: (c) 2017- StratoDem Analytics. All rights reserved.
Requires-Dist: slackclient ==2.9.3
Requires-Dist: numpy >=1.19
Requires-Dist: pandas ==1.3.4
Requires-Dist: joblib
Requires-Dist: dask ==2022.1.1
Requires-Dist: xarray >=0.10.0
Requires-Dist: geopandas >=0.3.0
Requires-Dist: simpledbf >=0.2.6
Requires-Dist: python-snappy
Requires-Dist: pyarrow >=2.0.0
Requires-Dist: toolz
Requires-Dist: cloudpickle
Requires-Dist: fastparquet
